mxray/__init__.py
mxray/cli.py
mxray/colors.py
mxray/core.py
mxray/exporters.py
mxray/styles.py
mxray-0.1.1.dist-info/licenses/LICENSE.txt
mxray-0.1.1.dist-info/METADATA
mxray-0.1.1.dist-info/WHEEL
mxray-0.1.1.dist-info/entry_points.txt
mxray-0.1.1.dist-info/top_level.txt
mxray-0.1.1.dist-info/RECORD
