Metadata-Version: 2.4
Name: mxray
Version: 0.1.1
Summary: X-ray vision for your Python data structures - ASCII mind maps and tree visualizations
Author-email: Midhun Haridas <midhunharidas0@gmail.com>
License: MIT
Project-URL: Homepage, https://github.com/GxDrogers/mxray
Project-URL: Repository, https://github.com/GxDrogers/mxray
Project-URL: Documentation, https://github.com/GxDrogers/mxray/wiki
Project-URL: Issue Tracker, https://github.com/GxDrogers/mxray/issues
Keywords: visualization,data-structures,debug,ascii,tree,mindmap,xray,inspect
Classifier: Development Status :: 4 - Beta
Classifier: Intended Audience :: Developers
Classifier: License :: OSI Approved :: MIT License
Classifier: Operating System :: OS Independent
Classifier: Programming Language :: Python :: 3
Classifier: Programming Language :: Python :: 3.7
Classifier: Programming Language :: Python :: 3.8
Classifier: Programming Language :: Python :: 3.9
Classifier: Programming Language :: Python :: 3.10
Classifier: Programming Language :: Python :: 3.11
Classifier: Programming Language :: Python :: 3.12
License-File: LICENSE.txt
Requires-Dist: requests>=2.25.0; python_version >= "3.6"
Provides-Extra: dev
Requires-Dist: pytest>=6.0; extra == "dev"
Requires-Dist: pytest-cov; extra == "dev"
Requires-Dist: black; extra == "dev"
Requires-Dist: flake8; extra == "dev"
Requires-Dist: pre-commit; extra == "dev"
Dynamic: license-file
